{
    "scenes": [
        {
            "id": "day2_after_start",
            "background": "classroom",
            "bgm": "sunset_warm",
            "sunset": true,
            "next": "day2_after_eunsu_1"
        },
        { "id": "day2_after_eunsu_1", "character": "eunsu_normal", "next": "day2_after_eunsu_2" },
        { "id": "day2_after_eunsu_2", "character": "eunsu_normal", "next": "day2_after_eunsu_3" },
        { "id": "day2_after_eunsu_3", "character": "eunsu_normal", "next": "day2_after_eunsu_4" },
        { "id": "day2_after_eunsu_4", "character": "eunsu_normal", "next": "day2_after_eunsu_5" },
        { "id": "day2_after_eunsu_5", "character": "eunsu_normal", "next": "day2_after_eunsu_6" },
        { "id": "day2_after_eunsu_6", "character": "eunsu_normal", "next": "day2_after_eunsu_choice" },
        {
            "id": "day2_after_eunsu_choice",
            "type": "choice",
            "choices": [
                {
                    "index": 0,
                    "next": "day2_after_comply_1",
                    "stats": { "eunsu": { "affinity": 3, "control": 3 } },
                    "flag": "app_full_access"
                },
                {
                    "index": 1,
                    "next": "day2_after_refuse_1",
                    "stats": { "eunsu": { "affinity": -1, "danger": 2 } },
                    "flag": "app_refused"
                }
            ]
        },
        { "id": "day2_after_comply_1", "character": "eunsu_smile", "next": "day2_after_comply_2" },
        { "id": "day2_after_comply_2", "character": "eunsu_smile", "next": "day2_after_comply_3" },
        { "id": "day2_after_comply_3", "character": "eunsu_smile", "next": "day2_after_comply_4" },
        { "id": "day2_after_comply_4", "character": "eunsu_smile", "next": "day2_after_comply_5" },
        { "id": "day2_after_comply_5", "character": "eunsu_smile", "next": "day2_after_comply_6" },
        { "id": "day2_after_comply_6", "character": "eunsu_smile", "next": "day2_after_transition" },
        { "id": "day2_after_refuse_1", "character": "eunsu_serious", "next": "day2_after_refuse_2" },
        { "id": "day2_after_refuse_2", "character": "eunsu_serious", "next": "day2_after_refuse_3" },
        { "id": "day2_after_refuse_3", "character": "eunsu_normal", "next": "day2_after_refuse_4" },
        { "id": "day2_after_refuse_4", "character": "eunsu_normal", "next": "day2_after_transition" },
        { "id": "day2_after_transition", "next": "day2_after_choice" },
        {
            "id": "day2_after_choice",
            "type": "routeChoice",
            "choices": [
                {
                    "index": 0,
                    "next": "day2_after_sea_1",
                    "stats": { "sea": { "affinity": 3 } },
                    "flag": "day2_after_sea"
                },
                {
                    "index": 1,
                    "next": "day2_after_yuna_1",
                    "stats": { "yuna": { "trust": 3 } },
                    "flag": "day2_after_yuna"
                },
                {
                    "index": 2,
                    "next": "day2_after_riin_1",
                    "stats": { "riin": { "affinity": 3 } },
                    "flag": "day2_after_riin"
                },
                {
                    "index": 3,
                    "next": "day2_after_home_1",
                    "flag": "day2_after_home"
                }
            ]
        },
        {
            "id": "day2_after_sea_1",
            "background": "student_council",
            "character": "sea_smile",
            "next": "day2_after_sea_2"
        },
        { "id": "day2_after_sea_2", "character": "sea_smile", "next": "day2_after_sea_3" },
        { "id": "day2_after_sea_3", "character": "sea_smile", "next": "day2_after_sea_4" },
        { "id": "day2_after_sea_4", "character": "sea_smile", "next": "day2_after_sea_5" },
        { "id": "day2_after_sea_5", "character": "sea_smile", "next": "day2_after_sea_6" },
        { "id": "day2_after_sea_6", "character": "sea_smile", "next": "day2_after_sea_7" },
        { "id": "day2_after_sea_7", "character": "sea_smile", "next": "day2_after_sea_8" },
        { "id": "day2_after_sea_8", "character": "sea_smile", "next": "day2_after_sea_9" },
        { "id": "day2_after_sea_9", "character": "sea_smile", "next": "day2_after_sea_10" },
        { "id": "day2_after_sea_10", "character": "sea_smile", "next": "day2_after_sea_11" },
        { "id": "day2_after_sea_11", "character": "sea_smile", "next": "day2_after_sea_12" },
        { "id": "day2_after_sea_12", "character": "sea_smile", "next": "day2_after_sea_13" },
        { "id": "day2_after_sea_13", "character": "sea_smile", "next": "day2_after_sea_14" },
        { "id": "day2_after_sea_14", "character": "sea_smile", "next": "day2_after_sea_15" },
        { "id": "day2_after_sea_15", "character": "sea_sad", "flag": "day2_sea_vulnerability", "next": "day2_after_sea_16" },
        { "id": "day2_after_sea_16", "character": "sea_sad", "next": "day2_after_sea_17" },
        { "id": "day2_after_sea_17", "character": "sea_sad", "next": "day2_after_sea_18" },
        { "id": "day2_after_sea_18", "character": "sea_sad", "next": "day2_after_sea_19" },
        { "id": "day2_after_sea_19", "character": "sea_smile", "next": "day2_after_sea_20" },
        { "id": "day2_after_sea_20", "character": "sea_smile", "next": "day2_after_sea_21" },
        { "id": "day2_after_sea_21", "character": "sea_smile", "next": "day2_after_sea_22" },
        { "id": "day2_after_sea_22", "character": "sea_smile", "next": "day2_after_sea_23" },
        { "id": "day2_after_sea_23", "character": "sea_smile", "next": "day2_after_sea_24" },
        { "id": "day2_after_sea_24", "character": "sea_smile", "next": "day2_after_sea_25" },
        { "id": "day2_after_sea_25", "character": "sea_smile", "next": "day2_after_sea_26" },
        { "id": "day2_after_sea_26", "character": "sea_smile", "next": "day2_after_sea_27" },
        { "id": "day2_after_sea_27", "character": "sea_smile", "next": "day2_after_sea_28" },
        { "id": "day2_after_sea_28", "character": "sea_smile", "next": "day2_after_sea_29" },
        { "id": "day2_after_sea_29", "character": "sea_smile", "next": "day2_after_home_1" },
        {
            "id": "day2_after_yuna_1",
            "background": "library",
            "character": "yuna_normal",
            "next": "day2_after_yuna_2"
        },
        { "id": "day2_after_yuna_2", "character": "yuna_normal", "next": "day2_after_yuna_3" },
        { "id": "day2_after_yuna_3", "character": "yuna_normal", "next": "day2_after_yuna_4" },
        { "id": "day2_after_yuna_4", "character": "yuna_normal", "next": "day2_after_yuna_5" },
        { "id": "day2_after_yuna_5", "character": "yuna_normal", "next": "day2_after_yuna_6" },
        { "id": "day2_after_yuna_6", "character": "yuna_normal", "next": "day2_after_yuna_7" },
        { "id": "day2_after_yuna_7", "character": "yuna_normal", "next": "day2_after_yuna_8" },
        { "id": "day2_after_yuna_8", "character": "yuna_normal", "next": "day2_after_yuna_9" },
        { "id": "day2_after_yuna_9", "character": "yuna_normal", "next": "day2_after_yuna_10" },
        { "id": "day2_after_yuna_10", "character": "yuna_normal", "next": "day2_after_yuna_11" },
        { "id": "day2_after_yuna_11", "character": "yuna_normal", "next": "day2_after_yuna_12" },
        { "id": "day2_after_yuna_12", "character": "yuna_scared", "next": "day2_after_yuna_13" },
        { "id": "day2_after_yuna_13", "character": "yuna_normal", "next": "day2_after_yuna_14" },
        { "id": "day2_after_yuna_14", "character": "yuna_normal", "next": "day2_after_yuna_15" },
        { "id": "day2_after_yuna_15", "character": "yuna_normal", "next": "day2_after_yuna_16" },
        { "id": "day2_after_yuna_16", "character": "yuna_normal", "next": "day2_after_yuna_17" },
        { "id": "day2_after_yuna_17", "character": "yuna_normal", "next": "day2_after_yuna_18" },
        { "id": "day2_after_yuna_18", "character": "yuna_normal", "next": "day2_after_home_1" },
        {
            "id": "day2_after_riin_1",
            "background": "nurse_office",
            "character": "riin_smile",
            "next": "day2_after_riin_2"
        },
        { "id": "day2_after_riin_2", "character": "riin_smile", "next": "day2_after_riin_3" },
        { "id": "day2_after_riin_3", "character": "riin_smile", "next": "day2_after_riin_4" },
        { "id": "day2_after_riin_4", "character": "riin_smile", "next": "day2_after_riin_5" },
        { "id": "day2_after_riin_5", "character": "riin_smile", "next": "day2_after_riin_6" },
        { "id": "day2_after_riin_6", "character": "riin_smile", "next": "day2_after_riin_7" },
        { "id": "day2_after_riin_7", "character": "riin_cold", "next": "day2_after_riin_8" },
        { "id": "day2_after_riin_8", "character": "riin_smile", "next": "day2_after_riin_9" },
        { "id": "day2_after_riin_9", "character": "riin_smile", "next": "day2_after_riin_10" },
        { "id": "day2_after_riin_10", "character": "riin_smile", "next": "day2_after_riin_11" },
        { "id": "day2_after_riin_11", "character": "riin_smile", "next": "day2_after_riin_12" },
        { "id": "day2_after_riin_12", "character": "riin_smile", "next": "day2_after_riin_13" },
        { "id": "day2_after_riin_13", "character": "riin_smile", "next": "day2_after_home_1" },
        {
            "id": "day2_after_home_1",
            "background": "school_gate_evening",
            "next": "day2_after_home_check"
        },
        {
            "id": "day2_after_home_check",
            "type": "flagBranch",
            "flag": "seolhwa_greeted",
            "branches": {
                "true": "day2_after_home_2",
                "false": "day2_after_end"
            }
        },
        { "id": "day2_after_home_2", "character": null, "next": "day2_after_home_3" },
        { "id": "day2_after_home_3", "character": null, "next": "day2_after_seolhwa_1" },
        {
            "id": "day2_after_seolhwa_1",
            "type": "bgmChange",
            "bgm": null,
            "character": "seolhwa_fade",
            "glitch": {"silence": true, "silenceDuration": 3000},
            "next": "day2_after_seolhwa_2"
        },
        { "id": "day2_after_seolhwa_2", "character": "seolhwa_fade", "next": "day2_after_seolhwa_3" },
        {
            "id": "day2_after_seolhwa_3",
            "type": "bgmChange",
            "bgm": "sunset_warm",
            "character": null,
            "next": "day2_after_seolhwa_4"
        },
        { "id": "day2_after_seolhwa_4", "character": null, "next": "day2_after_seolhwa_5" },
        { "id": "day2_after_seolhwa_5", "character": null, "next": "day2_after_end" },
        { "id": "day2_after_end", "next": null }
    ],
    "mergePoints": {
        "day2_after_comply_6": "day2_after_transition",
        "day2_after_refuse_4": "day2_after_transition",
        "day2_after_sea_29": "day2_after_home_1",
        "day2_after_yuna_18": "day2_after_home_1",
        "day2_after_riin_13": "day2_after_home_1",
        "day2_after_seolhwa_5": "day2_after_end"
    }
}
